fastgl/__init__.py
fastgl/_fastgl.cpython-310-x86_64-linux-gnu.so
fastgl.libs/libgomp-a34b3233.so.1.0.0
fastgl-0.1.11.dist-info/METADATA
fastgl-0.1.11.dist-info/WHEEL
fastgl-0.1.11.dist-info/RECORD
