Metadata-Version: 2.1
Name: fastgl
Version: 0.1.11
Summary: Python bindings for the Fast Gauss-Legendre (FastGL) algorithm
Author-Email: Mathew Madhavacheril <mathewsyriac@gmail.com>
License: MIT
Project-URL: Homepage, https://github.com/msyriac/fastgl
Requires-Python: >=3.10
Requires-Dist: pybind11>=2.11
Provides-Extra: test
Requires-Dist: scipy>=1.0; extra == "test"
Requires-Dist: pytest-cov>=2.6; extra == "test"
Requires-Dist: coveralls>=1.5; extra == "test"
Requires-Dist: pytest>=4.6; extra == "test"
Requires-Dist: numpy; extra == "test"
